[ {
  "firstName" : "Alex",
  "lastName" : "Smithies",
  "commonName" : "",
  "rating" : 73,
  "assetId" : 184436,
  "position" : "GK",
  "lowestBin" : 30000,
  "searchPrice" : 1000,
  "maxListPrice" : 0,
  "minListPrice" : 0,
  "nation" : 14,
  "club" : 1961,
  "league" : 13,
  "customPrice" : false,
  "priceSet" : false,
  "bidAmount" : 0
}, {
  "firstName" : "Neil",
  "lastName" : "Etheridge",
  "commonName" : "",
  "rating" : 72,
  "assetId" : 193186,
  "position" : "GK",
  "lowestBin" : 29000,
  "searchPrice" : 1000,
  "maxListPrice" : 0,
  "minListPrice" : 0,
  "nation" : 181,
  "club" : 1961,
  "league" : 13,
  "customPrice" : false,
  "priceSet" : false,
  "bidAmount" : 0
}, {
  "firstName" : "John",
  "lastName" : "Ruddy",
  "commonName" : "",
  "rating" : 72,
  "assetId" : 163600,
  "position" : "GK",
  "lowestBin" : 8900,
  "searchPrice" : 1000,
  "maxListPrice" : 0,
  "minListPrice" : 0,
  "nation" : 14,
  "club" : 110,
  "league" : 13,
  "customPrice" : false,
  "priceSet" : false,
  "bidAmount" : 0
}, {
  "firstName" : "Joe",
  "lastName" : "Bennett",
  "commonName" : "",
  "rating" : 71,
  "assetId" : 190430,
  "position" : "LB",
  "lowestBin" : 30000,
  "searchPrice" : 1000,
  "maxListPrice" : 0,
  "minListPrice" : 0,
  "nation" : 14,
  "club" : 1961,
  "league" : 13,
  "customPrice" : false,
  "priceSet" : false,
  "bidAmount" : 0
}, {
  "firstName" : "Greg",
  "lastName" : "Cunningham",
  "commonName" : "",
  "rating" : 74,
  "assetId" : 198190,
  "position" : "LB",
  "lowestBin" : 29000,
  "searchPrice" : 1000,
  "maxListPrice" : 0,
  "minListPrice" : 0,
  "nation" : 25,
  "club" : 1961,
  "league" : 13,
  "customPrice" : false,
  "priceSet" : false,
  "bidAmount" : 0
}, {
  "firstName" : "Matt",
  "lastName" : "Doherty",
  "commonName" : "",
  "rating" : 74,
  "assetId" : 201417,
  "position" : "RWB",
  "lowestBin" : 11000,
  "searchPrice" : 1000,
  "maxListPrice" : 0,
  "minListPrice" : 0,
  "nation" : 25,
  "club" : 110,
  "league" : 13,
  "customPrice" : false,
  "priceSet" : false,
  "bidAmount" : 0
}, {
  "firstName" : "Dominic",
  "lastName" : "Iorfa",
  "commonName" : "",
  "rating" : 67,
  "assetId" : 218658,
  "position" : "RB",
  "lowestBin" : 9900,
  "searchPrice" : 1000,
  "maxListPrice" : 0,
  "minListPrice" : 0,
  "nation" : 14,
  "club" : 110,
  "league" : 13,
  "customPrice" : false,
  "priceSet" : false,
  "bidAmount" : 0
}, {
  "firstName" : "Sean",
  "lastName" : "Morrison",
  "commonName" : "",
  "rating" : 74,
  "assetId" : 187033,
  "position" : "CB",
  "lowestBin" : 20000,
  "searchPrice" : 1000,
  "maxListPrice" : 0,
  "minListPrice" : 0,
  "nation" : 14,
  "club" : 1961,
  "league" : 13,
  "customPrice" : false,
  "priceSet" : false,
  "bidAmount" : 0
}, {
  "firstName" : "Bruno",
  "lastName" : "Ecuélé Manga",
  "commonName" : "",
  "rating" : 74,
  "assetId" : 188270,
  "position" : "CB",
  "lowestBin" : 19500,
  "searchPrice" : 1000,
  "maxListPrice" : 0,
  "minListPrice" : 0,
  "nation" : 115,
  "club" : 1961,
  "league" : 13,
  "customPrice" : false,
  "priceSet" : false,
  "bidAmount" : 0
}, {
  "firstName" : "Kortney",
  "lastName" : "Hause",
  "commonName" : "",
  "rating" : 67,
  "assetId" : 210635,
  "position" : "CB",
  "lowestBin" : 12500,
  "searchPrice" : 1000,
  "maxListPrice" : 0,
  "minListPrice" : 0,
  "nation" : 14,
  "club" : 110,
  "league" : 13,
  "customPrice" : false,
  "priceSet" : false,
  "bidAmount" : 0
}, {
  "firstName" : "Conor",
  "lastName" : "Coady",
  "commonName" : "",
  "rating" : 73,
  "assetId" : 202048,
  "position" : "CB",
  "lowestBin" : 12000,
  "searchPrice" : 1000,
  "maxListPrice" : 0,
  "minListPrice" : 0,
  "nation" : 14,
  "club" : 110,
  "league" : 13,
  "customPrice" : false,
  "priceSet" : false,
  "bidAmount" : 0
}, {
  "firstName" : "Ryan",
  "lastName" : "Bennett",
  "commonName" : "",
  "rating" : 71,
  "assetId" : 183774,
  "position" : "CB",
  "lowestBin" : 11750,
  "searchPrice" : 1000,
  "maxListPrice" : 0,
  "minListPrice" : 0,
  "nation" : 14,
  "club" : 110,
  "league" : 13,
  "customPrice" : false,
  "priceSet" : false,
  "bidAmount" : 0
}, {
  "firstName" : "Juan",
  "lastName" : "Foyth",
  "commonName" : "",
  "rating" : 70,
  "assetId" : 237221,
  "position" : "CB",
  "lowestBin" : 9300,
  "searchPrice" : 1000,
  "maxListPrice" : 0,
  "minListPrice" : 0,
  "nation" : 52,
  "club" : 18,
  "league" : 13,
  "customPrice" : false,
  "priceSet" : false,
  "bidAmount" : 0
}, {
  "firstName" : "Yangel",
  "lastName" : "Herrera",
  "commonName" : "",
  "rating" : 68,
  "assetId" : 234060,
  "position" : "CDM",
  "lowestBin" : 16500,
  "searchPrice" : 1000,
  "maxListPrice" : 0,
  "minListPrice" : 0,
  "nation" : 61,
  "club" : 10,
  "league" : 13,
  "customPrice" : false,
  "priceSet" : false,
  "bidAmount" : 0
}, {
  "firstName" : "Leandro",
  "lastName" : "Bacuna",
  "commonName" : "",
  "rating" : 69,
  "assetId" : 198133,
  "position" : "CDM",
  "lowestBin" : 9100,
  "searchPrice" : 1000,
  "maxListPrice" : 0,
  "minListPrice" : 0,
  "nation" : 85,
  "club" : 1961,
  "league" : 13,
  "customPrice" : false,
  "priceSet" : false,
  "bidAmount" : 0
}, {
  "firstName" : "Claudio",
  "lastName" : "Gomes",
  "commonName" : "",
  "rating" : 66,
  "assetId" : 245035,
  "position" : "CDM",
  "lowestBin" : 9000,
  "searchPrice" : 1000,
  "maxListPrice" : 0,
  "minListPrice" : 0,
  "nation" : 18,
  "club" : 10,
  "league" : 13,
  "customPrice" : false,
  "priceSet" : false,
  "bidAmount" : 0
}, {
  "firstName" : "Anthony",
  "lastName" : "Caceres",
  "commonName" : "",
  "rating" : 65,
  "assetId" : 209886,
  "position" : "CM",
  "lowestBin" : 22500,
  "searchPrice" : 1000,
  "maxListPrice" : 0,
  "minListPrice" : 0,
  "nation" : 195,
  "club" : 10,
  "league" : 13,
  "customPrice" : false,
  "priceSet" : false,
  "bidAmount" : 0
}, {
  "firstName" : "Romain",
  "lastName" : "Saïss",
  "commonName" : "",
  "rating" : 74,
  "assetId" : 208295,
  "position" : "CM",
  "lowestBin" : 9900,
  "searchPrice" : 1000,
  "maxListPrice" : 0,
  "minListPrice" : 0,
  "nation" : 129,
  "club" : 110,
  "league" : 13,
  "customPrice" : false,
  "priceSet" : false,
  "bidAmount" : 0
}, {
  "firstName" : "Joe",
  "lastName" : "Ralls",
  "commonName" : "",
  "rating" : 74,
  "assetId" : 204464,
  "position" : "CM",
  "lowestBin" : 7900,
  "searchPrice" : 1000,
  "maxListPrice" : 0,
  "minListPrice" : 0,
  "nation" : 14,
  "club" : 1961,
  "league" : 13,
  "customPrice" : false,
  "priceSet" : false,
  "bidAmount" : 0
}, {
  "firstName" : "Stuart",
  "lastName" : "O'Keefe",
  "commonName" : "",
  "rating" : 65,
  "assetId" : 189492,
  "position" : "CM",
  "lowestBin" : 7400,
  "searchPrice" : 1000,
  "maxListPrice" : 0,
  "minListPrice" : 0,
  "nation" : 14,
  "club" : 1961,
  "league" : 13,
  "customPrice" : false,
  "priceSet" : false,
  "bidAmount" : 0
}, {
  "firstName" : "Lee",
  "lastName" : "Tomlin",
  "commonName" : "",
  "rating" : 71,
  "assetId" : 172904,
  "position" : "CAM",
  "lowestBin" : 14250,
  "searchPrice" : 1000,
  "maxListPrice" : 0,
  "minListPrice" : 0,
  "nation" : 14,
  "club" : 1961,
  "league" : 13,
  "customPrice" : false,
  "priceSet" : false,
  "bidAmount" : 0
}, {
  "firstName" : "Phil",
  "lastName" : "Foden",
  "commonName" : "",
  "rating" : 73,
  "assetId" : 237692,
  "position" : "CAM",
  "lowestBin" : 7500,
  "searchPrice" : 1000,
  "maxListPrice" : 0,
  "minListPrice" : 0,
  "nation" : 14,
  "club" : 10,
  "league" : 13,
  "customPrice" : false,
  "priceSet" : false,
  "bidAmount" : 0
}, {
  "firstName" : "Kadeem",
  "lastName" : "Harris",
  "commonName" : "",
  "rating" : 65,
  "assetId" : 197170,
  "position" : "LM",
  "lowestBin" : 8000,
  "searchPrice" : 1000,
  "maxListPrice" : 0,
  "minListPrice" : 0,
  "nation" : 14,
  "club" : 1961,
  "league" : 13,
  "customPrice" : false,
  "priceSet" : false,
  "bidAmount" : 0
}, {
  "firstName" : "Sullay",
  "lastName" : "Kaikai",
  "commonName" : "",
  "rating" : 67,
  "assetId" : 212493,
  "position" : "LM",
  "lowestBin" : 6400,
  "searchPrice" : 1000,
  "maxListPrice" : 0,
  "minListPrice" : 0,
  "nation" : 14,
  "club" : 1799,
  "league" : 13,
  "customPrice" : false,
  "priceSet" : false,
  "bidAmount" : 0
}, {
  "firstName" : "Brahim",
  "lastName" : "Díaz",
  "commonName" : "Brahim Díaz",
  "rating" : 69,
  "assetId" : 231410,
  "position" : "LW",
  "lowestBin" : 10000,
  "searchPrice" : 1000,
  "maxListPrice" : 0,
  "minListPrice" : 0,
  "nation" : 45,
  "club" : 10,
  "league" : 13,
  "customPrice" : false,
  "priceSet" : false,
  "bidAmount" : 0
}, {
  "firstName" : "Josh",
  "lastName" : "Murphy",
  "commonName" : "",
  "rating" : 69,
  "assetId" : 206083,
  "position" : "LW",
  "lowestBin" : 7000,
  "searchPrice" : 1000,
  "maxListPrice" : 0,
  "minListPrice" : 0,
  "nation" : 14,
  "club" : 1961,
  "league" : 13,
  "customPrice" : false,
  "priceSet" : false,
  "bidAmount" : 0
}, {
  "firstName" : "Lazar",
  "lastName" : "Marković",
  "commonName" : "",
  "rating" : 74,
  "assetId" : 212125,
  "position" : "RM",
  "lowestBin" : 6500,
  "searchPrice" : 1000,
  "maxListPrice" : 0,
  "minListPrice" : 0,
  "nation" : 51,
  "club" : 144,
  "league" : 13,
  "customPrice" : false,
  "priceSet" : false,
  "bidAmount" : 0
}, {
  "firstName" : "Nathaniel",
  "lastName" : "Mendez-Laing",
  "commonName" : "",
  "rating" : 71,
  "assetId" : 194964,
  "position" : "RW",
  "lowestBin" : 19750,
  "searchPrice" : 1000,
  "maxListPrice" : 0,
  "minListPrice" : 0,
  "nation" : 14,
  "club" : 1961,
  "league" : 13,
  "customPrice" : false,
  "priceSet" : false,
  "bidAmount" : 0
}, {
  "firstName" : "Leonardo B.",
  "lastName" : "Lohner Maia",
  "commonName" : "Léo Bonatini",
  "rating" : 73,
  "assetId" : 220685,
  "position" : "ST",
  "lowestBin" : 13000,
  "searchPrice" : 1000,
  "maxListPrice" : 0,
  "minListPrice" : 0,
  "nation" : 54,
  "club" : 110,
  "league" : 13,
  "customPrice" : false,
  "priceSet" : false,
  "bidAmount" : 0
}, {
  "firstName" : "Collin",
  "lastName" : "Quaner",
  "commonName" : "",
  "rating" : 69,
  "assetId" : 199741,
  "position" : "ST",
  "lowestBin" : 9900,
  "searchPrice" : 1000,
  "maxListPrice" : 0,
  "minListPrice" : 0,
  "nation" : 21,
  "club" : 1939,
  "league" : 13,
  "customPrice" : false,
  "priceSet" : false,
  "bidAmount" : 0
} ]